odoo10_addon_hr_employee_birth_name-10.0.1.0.0-py2.7-nspkg.pth
odoo/addons/hr_employee_birth_name/__manifest__.py
odoo/addons/hr_employee_birth_name/__init__.py
odoo/addons/hr_employee_birth_name/README.rst
odoo/addons/hr_employee_birth_name/models/hr_employee.py
odoo/addons/hr_employee_birth_name/models/__init__.py
odoo/addons/hr_employee_birth_name/i18n/hr_employee_birth_name.pot
odoo/addons/hr_employee_birth_name/views/hr_employee_view.xml
odoo/addons/hr_employee_birth_name/static/description/icon.png
odoo10_addon_hr_employee_birth_name-10.0.1.0.0.dist-info/top_level.txt
odoo10_addon_hr_employee_birth_name-10.0.1.0.0.dist-info/WHEEL
odoo10_addon_hr_employee_birth_name-10.0.1.0.0.dist-info/RECORD
odoo10_addon_hr_employee_birth_name-10.0.1.0.0.dist-info/metadata.json
odoo10_addon_hr_employee_birth_name-10.0.1.0.0.dist-info/DESCRIPTION.rst
odoo10_addon_hr_employee_birth_name-10.0.1.0.0.dist-info/METADATA
odoo10_addon_hr_employee_birth_name-10.0.1.0.0.dist-info/namespace_packages.txt
